random_unicode_emoji/__init__.py
random_unicode_emoji/random_unicode_emoji.py
random_unicode_emoji/emoji/11.0/emoji-test.txt
random_unicode_emoji/emoji/12.0/emoji-test.txt
random_unicode_emoji/emoji/12.1/emoji-test.txt
random_unicode_emoji/emoji/13.0/emoji-test.txt
random_unicode_emoji/emoji/13.1/emoji-test.txt
random_unicode_emoji/emoji/14.0/emoji-test.txt
random_unicode_emoji/emoji/15.0/emoji-test.txt
random_unicode_emoji/emoji/15.1/emoji-test.txt
random_unicode_emoji/emoji/16.0/emoji-test.txt
random_unicode_emoji/emoji/17.0/emoji-test.txt
random_unicode_emoji/emoji/4.0/emoji-test.txt
random_unicode_emoji/emoji/5.0/emoji-test.txt
random_unicode_emoji/emoji/latest/emoji-test.txt
random_unicode_emoji-3.0.1.dist-info/licenses/LICENSE.rst
random_unicode_emoji-3.0.1.dist-info/METADATA
random_unicode_emoji-3.0.1.dist-info/WHEEL
random_unicode_emoji-3.0.1.dist-info/top_level.txt
random_unicode_emoji-3.0.1.dist-info/RECORD
