Metadata-Version: 2.4
Name: random_unicode_emoji
Version: 3.0.1
Summary: A simple Python package that returns random Unicode emojis.
Home-page: https://github.com/NicPWNs/random-unicode-emoji-py
Download-URL: https://github.com/NicPWNs/random-unicode-emoji-py/releases
Author: Nic Jones
Author-email: nic@nicpjones.com
License: MIT
Keywords: random unicode emoji function
Classifier: Programming Language :: Python :: 3
Classifier: License :: OSI Approved :: MIT License
Classifier: Operating System :: OS Independent
Requires-Python: >=3
License-File: LICENSE.rst
Dynamic: author
Dynamic: author-email
Dynamic: classifier
Dynamic: description
Dynamic: description-content-type
Dynamic: download-url
Dynamic: home-page
Dynamic: keywords
Dynamic: license
Dynamic: license-file
Dynamic: requires-python
Dynamic: summary
